jigsaw/Plugin.py
jigsaw/PluginLoader.py
jigsaw/__init__.py
Jigsaw-3.2.1.dist-info/LICENSE
Jigsaw-3.2.1.dist-info/METADATA
Jigsaw-3.2.1.dist-info/WHEEL
Jigsaw-3.2.1.dist-info/top_level.txt
Jigsaw-3.2.1.dist-info/RECORD
